frdomoticz/__init__.py
frdomoticz/lib.py
frdomoticz-0.0.3.dist-info/LICENSE
frdomoticz-0.0.3.dist-info/METADATA
frdomoticz-0.0.3.dist-info/WHEEL
frdomoticz-0.0.3.dist-info/top_level.txt
frdomoticz-0.0.3.dist-info/RECORD
