Metadata-Version: 2.1
Name: frdomoticz
Version: 0.0.3
Summary: Package for simplifying control of Freebox Revolution with Domoticz
Home-page: https://github.com/MatthieuF44/frdomoticz
Author: MatthieuF44
Author-email: matthieu.fleury44@gmail.com
License: UNKNOWN
Project-URL: Bug Tracker, https://github.com/MatthieuF44/frdomoticz/issues
Platform: UNKNOWN
Classifier: Development Status :: 2 - Pre-Alpha
Classifier: Programming Language :: Python :: 3
Classifier: License :: OSI Approved :: GNU General Public License v3 (GPLv3)
Classifier: Operating System :: OS Independent
Requires-Python: >=3.6
License-File: LICENSE
